{
  "generated_at": "2026-06-18T09:12:22.403506+00:00",
  "workspace": "<local-rre-root>/rsp_batch_runs",
  "model_id": "model_008",
  "run_name": "model_008_M0p6151_Z0p0004406_T6792",
  "source": "cumulative:saturation+continue_saturation+continue_saturation_resume:LOGS_continue_saturation_resume_1620000",
  "source_kind": "history_exact_rsp_columns",
  "cycle_count": 1027,
  "first_period": 1.0,
  "last_period": 1027.0,
  "rolling_window": 100,
  "fits": {
    "50": {
      "delta_r": {
        "available": true,
        "window_cycles": 50,
        "window_start_period": 978.0,
        "window_end_period": 1027.0,
        "first": 0.05929871740491688,
        "last": 0.06561666119978948,
        "median": 0.062375483812194155,
        "peak_to_peak": 0.006317943794872605,
        "fractional_peak_to_peak": 0.10128889442998552,
        "slope_per_cycle": 0.000128923482045557,
        "fractional_slope_per_cycle": 0.002066893499916276,
        "log_slope_per_cycle": 0.002066296124940926,
        "efolding_cycles": 483.95773864628876
      },
      "period_days": {
        "available": true,
        "window_cycles": 50,
        "window_start_period": 978.0,
        "window_end_period": 1027.0,
        "first": 0.6316223446440159,
        "last": 0.6316196496943357,
        "median": 0.6316218040684342,
        "peak_to_peak": 2.695710260236517e-06,
        "fractional_peak_to_peak": 4.267918306291474e-06,
        "slope_per_cycle": -5.4336210495314624e-08,
        "fractional_slope_per_cycle": -8.602649583235014e-08,
        "log_slope_per_cycle": -8.602656705174445e-08,
        "efolding_cycles": null
      },
      "gamma": {
        "available": true,
        "window_cycles": 50,
        "window_start_period": 978.0,
        "window_end_period": 1027.0,
        "first": 0.004161742113740718,
        "last": 0.004183774218415572,
        "median": 0.004172504550369676,
        "peak_to_peak": 2.236252066872401e-05,
        "fractional_peak_to_peak": 0.005359495813310194,
        "slope_per_cycle": 4.328454884131614e-07,
        "fractional_slope_per_cycle": 0.00010373757132866688,
        "log_slope_per_cycle": 0.00010372934170511366,
        "efolding_cycles": 9640.473790365353
      },
      "max_vsurf_div_cs": {
        "available": true,
        "window_cycles": 50,
        "window_start_period": 1018.0,
        "window_end_period": 1027.0,
        "first": 0.36986,
        "last": 0.37726,
        "median": 0.37354,
        "peak_to_peak": 0.007399999999999962,
        "fractional_peak_to_peak": 0.019810462065642135,
        "slope_per_cycle": 0.000822242424242422,
        "fractional_slope_per_cycle": 0.0022012165343535416,
        "log_slope_per_cycle": 0.0022011888058918656,
        "efolding_cycles": 454.29996614707727
      }
    },
    "100": {
      "delta_r": {
        "available": true,
        "window_cycles": 100,
        "window_start_period": 928.0,
        "window_end_period": 1027.0,
        "first": 0.05350397757549885,
        "last": 0.06561666119978948,
        "median": 0.05923763293447015,
        "peak_to_peak": 0.012112683624290632,
        "fractional_peak_to_peak": 0.20447615855430826,
        "slope_per_cycle": 0.00012227440225554882,
        "fractional_slope_per_cycle": 0.0020641338317959326,
        "log_slope_per_cycle": 0.0020616342082305345,
        "efolding_cycles": 485.05209896487065
      },
      "period_days": {
        "available": true,
        "window_cycles": 100,
        "window_start_period": 928.0,
        "window_end_period": 1027.0,
        "first": 0.6316222325400277,
        "last": 0.6316196496943357,
        "median": 0.631622091953177,
        "peak_to_peak": 2.7015756953741032e-06,
        "fractional_peak_to_peak": 4.277202665631865e-06,
        "slope_per_cycle": -1.6019693737671483e-08,
        "fractional_slope_per_cycle": -2.5362782495674718e-08,
        "log_slope_per_cycle": -2.536281524129835e-08,
        "efolding_cycles": null
      },
      "gamma": {
        "available": true,
        "window_cycles": 100,
        "window_start_period": 928.0,
        "window_end_period": 1027.0,
        "first": 0.004140341028382308,
        "last": 0.004183774218415572,
        "median": 0.004162004984065892,
        "peak_to_peak": 4.376360602713347e-05,
        "fractional_peak_to_peak": 0.01051502970195401,
        "slope_per_cycle": 4.2637287539789333e-07,
        "fractional_slope_per_cycle": 0.00010244410495187988,
        "log_slope_per_cycle": 0.00010244192489976483,
        "efolding_cycles": 9761.628366300794
      },
      "max_vsurf_div_cs": {
        "available": true,
        "window_cycles": 100,
        "window_start_period": 1018.0,
        "window_end_period": 1027.0,
        "first": 0.36986,
        "last": 0.37726,
        "median": 0.37354,
        "peak_to_peak": 0.007399999999999962,
        "fractional_peak_to_peak": 0.019810462065642135,
        "slope_per_cycle": 0.000822242424242422,
        "fractional_slope_per_cycle": 0.0022012165343535416,
        "log_slope_per_cycle": 0.0022011888058918656,
        "efolding_cycles": 454.29996614707727
      }
    },
    "250": {
      "delta_r": {
        "available": true,
        "window_cycles": 250,
        "window_start_period": 778.0,
        "window_end_period": 1027.0,
        "first": 0.039374622179251695,
        "last": 0.06561666119978948,
        "median": 0.05077977099673614,
        "peak_to_peak": 0.02624203902053779,
        "fractional_peak_to_peak": 0.5167813581164927,
        "slope_per_cycle": 0.00010485873603911139,
        "fractional_slope_per_cycle": 0.0020649706365523223,
        "log_slope_per_cycle": 0.0020502707298015897,
        "efolding_cycles": 487.7404654246675
      },
      "period_days": {
        "available": true,
        "window_cycles": 250,
        "window_start_period": 778.0,
        "window_end_period": 1027.0,
        "first": 0.6316293933537478,
        "last": 0.6316196496943357,
        "median": 0.6316237665724044,
        "peak_to_peak": 9.743659412086991e-06,
        "fractional_peak_to_peak": 1.542636602318234e-05,
        "slope_per_cycle": -4.069514488927012e-08,
        "fractional_slope_per_cycle": -6.44294072563293e-08,
        "log_slope_per_cycle": -6.442926806207269e-08,
        "efolding_cycles": null
      },
      "gamma": {
        "available": true,
        "window_cycles": 250,
        "window_start_period": 778.0,
        "window_end_period": 1027.0,
        "first": 0.004092597447197941,
        "last": 0.004183774218415572,
        "median": 0.004129731507876481,
        "peak_to_peak": 9.203386487088676e-05,
        "fractional_peak_to_peak": 0.022285677578640174,
        "slope_per_cycle": 3.688500748793772e-07,
        "fractional_slope_per_cycle": 8.931575192621686e-05,
        "log_slope_per_cycle": 8.91910152453913e-05,
        "efolding_cycles": 11211.891660260839
      },
      "max_vsurf_div_cs": {
        "available": true,
        "window_cycles": 250,
        "window_start_period": 1018.0,
        "window_end_period": 1027.0,
        "first": 0.36986,
        "last": 0.37726,
        "median": 0.37354,
        "peak_to_peak": 0.007399999999999962,
        "fractional_peak_to_peak": 0.019810462065642135,
        "slope_per_cycle": 0.000822242424242422,
        "fractional_slope_per_cycle": 0.0022012165343535416,
        "log_slope_per_cycle": 0.0022011888058918656,
        "efolding_cycles": 454.29996614707727
      }
    },
    "500": {
      "delta_r": {
        "available": true,
        "window_cycles": 500,
        "window_start_period": 528.0,
        "window_end_period": 1027.0,
        "first": 0.00706628279822219,
        "last": 0.06561666119978948,
        "median": 0.03933456667367219,
        "peak_to_peak": 0.05855037840156729,
        "fractional_peak_to_peak": 1.4885222681442891,
        "slope_per_cycle": 0.00010911440983823396,
        "fractional_slope_per_cycle": 0.0027740081832722343,
        "log_slope_per_cycle": 0.0038499783773718165,
        "efolding_cycles": 259.74171851911774
      },
      "period_days": {
        "available": true,
        "window_cycles": 500,
        "window_start_period": 528.0,
        "window_end_period": 1027.0,
        "first": 0.6316406692611054,
        "last": 0.6316196496943357,
        "median": 0.6316293940236964,
        "peak_to_peak": 2.1639826009001162e-05,
        "fractional_peak_to_peak": 3.4260321343102844e-05,
        "slope_per_cycle": -3.655202989941675e-08,
        "fractional_slope_per_cycle": -5.7869425085757566e-08,
        "log_slope_per_cycle": -5.786941699733894e-08,
        "efolding_cycles": null
      },
      "gamma": {
        "available": true,
        "window_cycles": 500,
        "window_start_period": 528.0,
        "window_end_period": 1027.0,
        "first": 0.003986086924148662,
        "last": 0.004183774218415572,
        "median": 0.004092398076977574,
        "peak_to_peak": 0.00023470111746947547,
        "fractional_peak_to_peak": 0.05735051015438194,
        "slope_per_cycle": 3.0648604413111507e-07,
        "fractional_slope_per_cycle": 7.489155218191023e-05,
        "log_slope_per_cycle": 7.48351702903983e-05,
        "efolding_cycles": 13362.700934861166
      },
      "max_vsurf_div_cs": {
        "available": true,
        "window_cycles": 500,
        "window_start_period": 528.0,
        "window_end_period": 1027.0,
        "first": 0.03832,
        "last": 0.37726,
        "median": 0.04164,
        "peak_to_peak": 0.33893999999999996,
        "fractional_peak_to_peak": 8.139769452449567,
        "slope_per_cycle": 0.0007136954314071338,
        "fractional_slope_per_cycle": 0.017139659736002254,
        "log_slope_per_cycle": 0.0047593016708224484,
        "efolding_cycles": 210.11485910435917
      }
    }
  },
  "latest_rolling": {
    "window_start_period": 928.0,
    "window_end_period": 1027.0,
    "gamma_peak_to_peak": 4.376360602713347e-05,
    "period_fractional_peak_to_peak": 4.277202665631865e-06,
    "delta_r_fractional_peak_to_peak": 0.20447615855430826
  },
  "growth_outlook": {
    "status": "amplitude still growing",
    "tolerance": 0.001,
    "delta_r_fractional_peak_to_peak": 0.20447615855430826,
    "delta_r_criterion_factor": 204.47615855430826,
    "log_slope_per_cycle": 0.0020616342082305345,
    "efolding_cycles": 485.05209896487065,
    "doubling_cycles": 336.21249482218366,
    "fit_window_cycles": 100,
    "max_vsurf_div_cs_latest": 0.37726,
    "max_vsurf_div_cs_log_slope_per_cycle": 0.0022011888058918656,
    "max_vsurf_div_cs_efolding_cycles": 454.29996614707727,
    "max_vsurf_div_cs_fit_window_cycles": 100,
    "cycles_to_vsurf_div_cs_0p8": 341.486891419016,
    "cycles_to_vsurf_div_cs_1p0": 442.860999227
  }
}
