{
  "generated_at": "2026-06-19T03:50:24.768687+00:00",
  "workspace": "<local-rre-root>/rsp_batch_runs",
  "model_id": "model_009",
  "run_name": "model_009_M0p6668_Z0p0001120_T6852",
  "source": "cumulative:saturation+saturation_resume:LOGS_saturation_resume_130000",
  "source_kind": "history_exact_rsp_columns",
  "cycle_count": 233,
  "first_period": 1.0,
  "last_period": 233.0,
  "rolling_window": 100,
  "fits": {
    "50": {
      "delta_r": {
        "available": true,
        "window_cycles": 50,
        "window_start_period": 184.0,
        "window_end_period": 233.0,
        "first": 0.0030480568890931536,
        "last": 0.003623491612470886,
        "median": 0.0034855918662151097,
        "peak_to_peak": 0.0009054605251952452,
        "fractional_peak_to_peak": 0.2597723887215904,
        "slope_per_cycle": 9.757782913670316e-06,
        "fractional_slope_per_cycle": 0.0027994622687325618,
        "log_slope_per_cycle": 0.002806782130290971,
        "efolding_cycles": 356.2798797982702
      },
      "period_days": {
        "available": true,
        "window_cycles": 50,
        "window_start_period": 184.0,
        "window_end_period": 233.0,
        "first": 0.5171484729533269,
        "last": 0.4993505409631568,
        "median": 0.4993285290518866,
        "peak_to_peak": 0.029518323426126314,
        "fractional_peak_to_peak": 0.05911603625407709,
        "slope_per_cycle": -3.2888667933979916e-05,
        "fractional_slope_per_cycle": -6.586578979660575e-05,
        "log_slope_per_cycle": -6.540402789204638e-05,
        "efolding_cycles": null
      },
      "gamma": {
        "available": true,
        "window_cycles": 50,
        "window_start_period": 184.0,
        "window_end_period": 233.0,
        "first": 0.00821034914878034,
        "last": 0.005014418465387268,
        "median": 0.005046654924442979,
        "peak_to_peak": 0.005084203462958899,
        "fractional_peak_to_peak": 1.0074402825392434,
        "slope_per_cycle": -4.100681021579834e-06,
        "fractional_slope_per_cycle": -0.0008125542726764588,
        "log_slope_per_cycle": -0.0010923511427648972,
        "efolding_cycles": null
      },
      "max_vsurf_div_cs": {
        "available": true,
        "window_cycles": 50,
        "window_start_period": 184.0,
        "window_end_period": 233.0,
        "first": 0.02009,
        "last": 0.02459,
        "median": 0.024165,
        "peak_to_peak": 0.007949999999999999,
        "fractional_peak_to_peak": 0.32898820608317814,
        "slope_per_cycle": 6.812340936374551e-05,
        "fractional_slope_per_cycle": 0.002819094118094166,
        "log_slope_per_cycle": 0.0028521106222522746,
        "efolding_cycles": 350.61753643002567
      }
    },
    "100": {
      "delta_r": {
        "available": true,
        "window_cycles": 100,
        "window_start_period": 134.0,
        "window_end_period": 233.0,
        "first": 0.0026681696501071883,
        "last": 0.003623491612470886,
        "median": 0.003267910327859447,
        "peak_to_peak": 0.0012853477641812106,
        "fractional_peak_to_peak": 0.3933240619313877,
        "slope_per_cycle": 8.972618914716608e-06,
        "fractional_slope_per_cycle": 0.0027456747629283546,
        "log_slope_per_cycle": 0.0027574687047147296,
        "efolding_cycles": 362.6514412621244
      },
      "period_days": {
        "available": true,
        "window_cycles": 100,
        "window_start_period": 134.0,
        "window_end_period": 233.0,
        "first": 0.5107054751427064,
        "last": 0.4993505409631568,
        "median": 0.5008335506871959,
        "peak_to_peak": 0.029518323426126314,
        "fractional_peak_to_peak": 0.05893839058031174,
        "slope_per_cycle": -7.460854341679663e-06,
        "fractional_slope_per_cycle": -1.489687408409958e-05,
        "log_slope_per_cycle": -1.520514590828945e-05,
        "efolding_cycles": null
      },
      "gamma": {
        "available": true,
        "window_cycles": 100,
        "window_start_period": 134.0,
        "window_end_period": 233.0,
        "first": 0.007609844362134793,
        "last": 0.005014418465387268,
        "median": 0.005014852279844825,
        "peak_to_peak": 0.005084203462958899,
        "fractional_peak_to_peak": 1.0138291577187235,
        "slope_per_cycle": -6.848294216779349e-07,
        "fractional_slope_per_cycle": -0.0001365602381610183,
        "log_slope_per_cycle": -0.00010663878323888669,
        "efolding_cycles": null
      },
      "max_vsurf_div_cs": {
        "available": true,
        "window_cycles": 100,
        "window_start_period": 134.0,
        "window_end_period": 233.0,
        "first": 0.01763,
        "last": 0.02459,
        "median": 0.022255,
        "peak_to_peak": 0.010409999999999999,
        "fractional_peak_to_peak": 0.46776005392046727,
        "slope_per_cycle": 6.209120912091209e-05,
        "fractional_slope_per_cycle": 0.0027899891764058453,
        "log_slope_per_cycle": 0.002777971339127983,
        "efolding_cycles": 359.97491619690516
      }
    },
    "250": {
      "delta_r": {
        "available": false,
        "reason": "only 233 rows for 250-cycle window"
      },
      "period_days": {
        "available": false,
        "reason": "only 233 rows for 250-cycle window"
      },
      "gamma": {
        "available": false,
        "reason": "only 233 rows for 250-cycle window"
      },
      "max_vsurf_div_cs": {
        "available": false,
        "reason": "only 233 rows for 250-cycle window"
      }
    },
    "500": {
      "delta_r": {
        "available": false,
        "reason": "only 233 rows for 500-cycle window"
      },
      "period_days": {
        "available": false,
        "reason": "only 233 rows for 500-cycle window"
      },
      "gamma": {
        "available": false,
        "reason": "only 233 rows for 500-cycle window"
      },
      "max_vsurf_div_cs": {
        "available": false,
        "reason": "only 233 rows for 500-cycle window"
      }
    }
  },
  "latest_rolling": {
    "window_start_period": 134.0,
    "window_end_period": 233.0,
    "gamma_peak_to_peak": 0.005084203462958899,
    "period_fractional_peak_to_peak": 0.05893839058031174,
    "delta_r_fractional_peak_to_peak": 0.3933240619313877
  },
  "growth_outlook": {
    "status": "amplitude still growing",
    "tolerance": 0.001,
    "delta_r_fractional_peak_to_peak": 0.3933240619313877,
    "delta_r_criterion_factor": 393.3240619313877,
    "log_slope_per_cycle": 0.0027574687047147296,
    "efolding_cycles": 362.6514412621244,
    "doubling_cycles": 251.37082403684212,
    "fit_window_cycles": 100,
    "max_vsurf_div_cs_latest": 0.02459,
    "max_vsurf_div_cs_log_slope_per_cycle": 0.002777971339127983,
    "max_vsurf_div_cs_efolding_cycles": 359.97491619690516,
    "max_vsurf_div_cs_fit_window_cycles": 100,
    "cycles_to_vsurf_div_cs_0p8": 1253.5305250963913,
    "cycles_to_vsurf_div_cs_1p0": 1333.856606280604
  }
}
